CHANGES.txt
README.txt
setup.py
src/ws/__init__.py
src/ws.plusfeed.egg-info/PKG-INFO
src/ws.plusfeed.egg-info/SOURCES.txt
src/ws.plusfeed.egg-info/dependency_links.txt
src/ws.plusfeed.egg-info/entry_points.txt
src/ws.plusfeed.egg-info/namespace_packages.txt
src/ws.plusfeed.egg-info/not-zip-safe
src/ws.plusfeed.egg-info/requires.txt
src/ws.plusfeed.egg-info/top_level.txt
src/ws/plusfeed/__init__.py
src/ws/plusfeed/main.py