Metadata-Version: 1.0
Name: ws.plusfeed
Version: 1.1
Summary: Creates anAtom feed from the public timeline of Google Plus users.
Home-page: https://bitbucket.org/wosc/plusfeed/
Author: Wolfgang Schnerring <wosc@wosc.de>
Author-email: wosc@wosc.de
License: ZPL 2.1
Platform: UNKNOWN
